.gitignore
.travis.yml
LICENSE
MANIFEST.in
README.md
changelog.rst
requirements.txt
setup.cfg
setup.py
tox.ini
vagrant wheel install problems.txt
edtf2/__init__.py
edtf2/appsettings.py
edtf2/convert.py
edtf2/fields.py
edtf2/jdutil.py
edtf2/tests.py
edtf2.egg-info/PKG-INFO
edtf2.egg-info/SOURCES.txt
edtf2.egg-info/dependency_links.txt
edtf2.egg-info/requires.txt
edtf2.egg-info/top_level.txt
edtf2/natlang/__init__.py
edtf2/natlang/en.py
edtf2/natlang/tests.py
edtf2/parser/__init__.py
edtf2/parser/edtf_exceptions.py
edtf2/parser/grammar.py
edtf2/parser/grammar_test.py
edtf2/parser/parser_classes.py
edtf2/parser/parser_classes_tests.py
edtf2/parser/tests.py