Metadata-Version: 2.1
Name: edtf2
Version: 5.0.0
Summary: Python implementation of Library of Congress EDTF (Extended Date Time Format) specification
Home-page: https://github.com/saw-leipzig/python-edtf
Author: Sabine Müller
Author-email: muellers@saw-leipzig.de
License: MIT
Keywords: edtf
Platform: UNKNOWN
Classifier: Intended Audience :: Developers
Classifier: Intended Audience :: End Users/Desktop
Classifier: License :: OSI Approved :: MIT License
Classifier: Operating System :: MacOS :: MacOS X
Classifier: Operating System :: POSIX :: Linux
Classifier: Programming Language :: Python
Classifier: Programming Language :: Python :: 2.7
Classifier: Programming Language :: Python :: 3.6
Provides-Extra: test
